{"map_counts": {"pillars": 56, "great_divide": 54, "cage": 18, "empty": 53, "empty_large": 45, "ssspline": 32, "combustible_lemons": 23, "arena": 43, "ladder": 60, "compasss": 52, "recurve": 32, "diamonds": 41, "ssspiral": 27, "lol": 57, "attrition": 44}, "map_wins": {"pillars": 26, "great_divide": 31, "cage": 14, "empty": 31, "empty_large": 29, "ssspline": 17, "combustible_lemons": 16, "arena": 27, "ladder": 31, "compasss": 30, "recurve": 20, "diamonds": 31, "ssspiral": 20, "lol": 31, "attrition": 19}}